README.rst
setup.cfg
setup.py
take/__init__.py
take/_compat.py
take/directives.py
take/exceptions.py
take/parser.py
take/scanner.py
take/take_template.py
take/utils.py
take.egg-info/PKG-INFO
take.egg-info/SOURCES.txt
take.egg-info/dependency_links.txt
take.egg-info/not-zip-safe
take.egg-info/requires.txt
take.egg-info/top_level.txt